readyocr/__init__.py
readyocr/__main__.py
readyocr/exceptions.py
readyocr/entities/__init__.py
readyocr/entities/bbox.py
readyocr/entities/block.py
readyocr/entities/cell.py
readyocr/entities/character.py
readyocr/entities/children_mixin.py
readyocr/entities/document.py
readyocr/entities/draw_curve.py
readyocr/entities/draw_line.py
readyocr/entities/draw_rectangle.py
readyocr/entities/entity_list.py
readyocr/entities/entity_tag.py
readyocr/entities/field.py
readyocr/entities/figure.py
readyocr/entities/image.py
readyocr/entities/invoice.py
readyocr/entities/key.py
readyocr/entities/line.py
readyocr/entities/merged_cell.py
readyocr/entities/page.py
readyocr/entities/page_entity.py
readyocr/entities/paragraph.py
readyocr/entities/table.py
readyocr/entities/textbox.py
readyocr/entities/value.py
readyocr/entities/word.py
readyocr/parsers/google_document_ai_parser.py
readyocr/parsers/google_vision_parser.py
readyocr/parsers/pdf_parser.py
readyocr/parsers/readyocr_parser.py
readyocr/parsers/textract_parser.py
readyocr/utils/geometry_utils.py
readyocr/utils/languages.py
readyocr/utils/visualize.py
readyocr-0.0.43.dist-info/LICENSE
readyocr-0.0.43.dist-info/METADATA
readyocr-0.0.43.dist-info/WHEEL
readyocr-0.0.43.dist-info/top_level.txt
readyocr-0.0.43.dist-info/RECORD
