Metadata-Version: 2.1
Name: readyocr
Version: 0.0.43
Summary: A nice package OCR for Amazon Textract and Google Document AI
Author-email: Sy An <syan.vn@gmail.com>
License: Copyright 2023 Sy An
Project-URL: Homepage, https://github.com/syanng/readyocr
Project-URL: Bug Tracker, https://github.com/syanng/readyocr/issues
Keywords: ocr,textract,documentai
Classifier: Programming Language :: Python :: 3
Classifier: License :: OSI Approved :: MIT License
Classifier: Operating System :: OS Independent
Requires-Python: >=3.8
License-File: LICENSE
Requires-Dist: numpy
Requires-Dist: typing-extensions
Requires-Dist: Pillow
Requires-Dist: pdf2image
Requires-Dist: pdfminer.six
Requires-Dist: pypdf
Provides-Extra: all
Requires-Dist: amazon-textract-textractor ; extra == 'all'
Requires-Dist: google-cloud-documentai ; extra == 'all'
Provides-Extra: documentai
Requires-Dist: google-cloud-documentai ; extra == 'documentai'
Provides-Extra: textract
Requires-Dist: amazon-textract-textractor ; extra == 'textract'
